CHANGES.txt
LICENSE.txt
MANIFEST.in
README.rst
requirements.txt
setup.py
petrophysics/__init__.py
petrophysics.egg-info/PKG-INFO
petrophysics.egg-info/SOURCES.txt
petrophysics.egg-info/dependency_links.txt
petrophysics.egg-info/requires.txt
petrophysics.egg-info/top_level.txt
petrophysics/clayvolume/__init__.py
petrophysics/clayvolume/clayvolume.py
petrophysics/conversions/__init__.py
petrophysics/conversions/oil.py
petrophysics/conversions/temperature.py
petrophysics/lithology/__init__.py
petrophysics/lithology/lithology.py
petrophysics/permeability/__init__.py
petrophysics/permeability/permeability.py
petrophysics/porosity/__init__.py
petrophysics/porosity/porosity.py
petrophysics/reserves/__init__.py
petrophysics/reserves/volumetrics.py
petrophysics/resistivity/__init__.py
petrophysics/resistivity/resistivity.py
petrophysics/rockphysics/__init__.py
petrophysics/rockphysics/density.py
petrophysics/rockphysics/elastic.py
petrophysics/rockphysics/impedance.py
petrophysics/rockphysics/pwave.py
petrophysics/rockphysics/ratio.py
petrophysics/rockphysics/shear.py
petrophysics/salinity/__init__.py
petrophysics/salinity/salinity.py
petrophysics/saturation/__init__.py
petrophysics/saturation/mvi.py
petrophysics/saturation/soil.py
petrophysics/saturation/sw.py
petrophysics/saturation/sxo.py
petrophysics/temperature/__init__.py
petrophysics/temperature/temperature.py