Metadata-Version: 1.0
Name: petrophysics
Version: 0.1.3
Summary: A package containing useful functions for well log interpretation
Home-page: http://pypi.python.org/pypi/petrophysics/
Author: Mihai
Author-email: m_iorgandopol@yahoo.com
License: ['MIT']
Platform: UNKNOWN
